<?xml version="1.0" encoding="UTF-8"?>
<!-- 
 * Copyright (C) 
-->
<tagset type="config" xmlns:xi="http://www.w3.org/2001/XInclude">

    <xi:include href="Grouping-MIM11.xml"/>
    
    <name>Grouping for MIM 1.2</name>
    
    <desc lang="en">Deviations and additions to generic grouping for MIM 1.2 metamodel.</desc>  
    
    <tagged-values>

        <tv norm="space" id="CFG-TV-ISDERIVED">
            <stereo minmax="0..1">stereotype-name-interface</stereo>
            <stereo minmax="0..1">stereotype-name-conceptual</stereo>
        </tv>
        
        <tv norm="space"  id="CFG-TV-POSITION"><!-- origin="system" -->
            <stereo minmax="0..1">stereotype-name-interface</stereo>
            <stereo minmax="0..1">stereotype-name-conceptual</stereo>
        </tv>
    
    </tagged-values>
</tagset>